nysimplelog/__init__.py
nysimplelog/utils.py
nysimplelog-1.0.1.dist-info/LICENSE
nysimplelog-1.0.1.dist-info/METADATA
nysimplelog-1.0.1.dist-info/WHEEL
nysimplelog-1.0.1.dist-info/top_level.txt
nysimplelog-1.0.1.dist-info/RECORD
