Metadata-Version: 2.2
Name: nysimplelog
Version: 1.0.1
Summary: A simple Python library for logging with console and file output
Author-email: Naoyuki Yoshinori <1448309+naoyoshinori@users.noreply.github.com>
License: MIT License
Project-URL: Homepage, https://github.com/naoyoshinori/nysimplelog
Requires-Python: >=3.10
License-File: LICENSE
Provides-Extra: dev
Requires-Dist: pytest>=7.0; extra == "dev"
Requires-Dist: build>=1.0.0; extra == "dev"
Requires-Dist: twine>=4.0.0; extra == "dev"
